custom_image_search_client/__init__.py
custom_image_search_client/_configuration.py
custom_image_search_client/_custom_image_search_client.py
custom_image_search_client/version.py
custom_image_search_client/aio/__init__.py
custom_image_search_client/aio/_configuration.py
custom_image_search_client/aio/_custom_image_search_client.py
custom_image_search_client/aio/operations/__init__.py
custom_image_search_client/aio/operations/_custom_instance_operations.py
custom_image_search_client/models/__init__.py
custom_image_search_client/models/_custom_image_search_client_enums.py
custom_image_search_client/models/_models.py
custom_image_search_client/models/_models_py3.py
custom_image_search_client/operations/__init__.py
custom_image_search_client/operations/_custom_instance_operations.py
microsoft_bing_customimagesearch-1.0.0.dist-info/LICENSE.txt
microsoft_bing_customimagesearch-1.0.0.dist-info/METADATA
microsoft_bing_customimagesearch-1.0.0.dist-info/WHEEL
microsoft_bing_customimagesearch-1.0.0.dist-info/top_level.txt
microsoft_bing_customimagesearch-1.0.0.dist-info/RECORD
